gnosys/__init__.py
gnosys/cli.py
gnosys/templates/.env.example
gnosys/templates/servers.json.template
gnosys-0.2.0.dist-info/licenses/LICENSE
gnosys-0.2.0.dist-info/METADATA
gnosys-0.2.0.dist-info/WHEEL
gnosys-0.2.0.dist-info/entry_points.txt
gnosys-0.2.0.dist-info/top_level.txt
gnosys-0.2.0.dist-info/RECORD
