Metadata-Version: 2.4
Name: gnosys
Version: 0.2.0
Summary: GNO.SYS - Compound Intelligence Ecosystem Meta-Package
Author-email: Isaac Wostrel-Rubin <isaac@sanctuary.systems>
License-Expression: LicenseRef-GPBL-1.0
Project-URL: Homepage, https://github.com/sancovp/gnosys
Project-URL: Repository, https://github.com/sancovp/gnosys
Project-URL: Issues, https://github.com/sancovp/gnosys/issues
Requires-Python: >=3.10
License-File: LICENSE
Requires-Dist: gnosys-strata
Requires-Dist: carton-mcp
Requires-Dist: canopy-mcp
Requires-Dist: opera-mcp
Requires-Dist: flightsim-mcp
Requires-Dist: brain-agent
Requires-Dist: sanctuary-system-mcp
Requires-Dist: starlog-mcp
Requires-Dist: starship-mcp
Requires-Dist: payload-discovery
Requires-Dist: starsystem
Requires-Dist: giint-llm-intelligence
Requires-Dist: heaven-framework
Requires-Dist: toot-mcp
Requires-Dist: pydantic-stack-core
Requires-Dist: seed-mcp
Requires-Dist: gnosys-treeshell
Requires-Dist: skill-manager-treeshell
Requires-Dist: python-dotenv
Requires-Dist: rich
Provides-Extra: dev
Requires-Dist: pytest; extra == "dev"
Requires-Dist: black; extra == "dev"
Requires-Dist: ruff; extra == "dev"
Dynamic: license-file
